{
  "passenger": "pasahero",
  "pasta": "pasta",
  "path": "landas",
  "patient": "pasyente, matiyaga",
  "pc": "PC, kompyuter",
  "pea": "gisantes",
  "peaceful": "mapayapa",
  "pear": "peras",
  "pence": "pens (British)",
  "pepper": "paminta",
  "perfect": "perpekto",
  "perfectly": "nang perpekto",
  "perform": "magsagawa, gumanap",
  "performance": "pagtatanghal",
  "perfume": "pabango",
  "perhaps": "marahil (pormal)",
  "permission": "pahintulot",
  "personality": "personalidad",
  "petrol": "gasolina",
  "photograph": "larawan (kamera)",
  "photographer": "litratista",
  "photography": "photography, pagkuha ng larawan",
  "physical": "pisikal",
  "physically": "nang pisikal",
  "pile": "tumpok (mga bagay)",
  "pilgrim": "peregrino",
  "pill": "tableta",
  "pilot": "piloto",
  "pity": "kawawa, habag",
  "planet": "planeta",
  "plant": "halaman, tanim, pabrika",
  "plastic": "plastik",
  "plate": "plato, pagkain",
  "playful": "malikot",
  "playground": "palaruan",
  "pleasant": "kaaya-aya",
  "pleased": "masayang-masaya",
  "pleasing": "nakakaaliw",
  "plenty": "sapat, marami",
  "plural": "pangmaramihan",
  "plus": "dagdag sa",
  "poison": "lason, pagkalason",
  "police": "pulis, kapulisan",
  "policeman": "pulis (lalaki)",
  "policewoman": "pulis (babae)",
  "polite": "magalang",
  "political": "politikal",
  "pollute": "magnalason",
  "popular": "sikat, popular",
  "population": "populasyon",
  "portrait": "larawan (tao)",
  "position": "posisyon",
  "possible": "posible",
  "possibly": "posibleng",
  "pour": "ibuhos",
  "power": "kapangyarihan",
  "powerful": "makapangyarihan",
  "precise": "tumpak",
  "predict": "hulaan, mahulaan",
  "prediction": "hula, hulaan",
  "prefer": "mas gusto",
  "prepare": "maghanda",
  "pressure": "presyon",
  "pretend": "magpanggap",
  "prevent": "pigilan",
  "pride": "pagmamalaki",
  "principal": "punong-guro, pangunahing",
  "print": "i-print",
  "printer": "printer",
  "private": "pribado",
  "pro": "pro, dalubhasa",
  "probably": "malamang na",
  "produce": "gumawa, gulay",
  "product": "produkto",
  "production": "produksyon",
  "professional": "propesyonal",
  "progressive": "progresibo",
  "promise": "pangako, mangako",
  "pronounce": "bigkasin",
  "pronunciation": "pagbigkas"
}